MANIFEST.in
setup.py
shinkenplugins/VERSION
shinkenplugins/__init__.py
shinkenplugins/argparse.py
shinkenplugins/old.py
shinkenplugins/perfdata.py
shinkenplugins/plugin.py
shinkenplugins/states.py
shinkenplugins/test.py
shinkenplugins/version.py
shinkenplugins.egg-info/PKG-INFO
shinkenplugins.egg-info/SOURCES.txt
shinkenplugins.egg-info/dependency_links.txt
shinkenplugins.egg-info/namespace_packages.txt
shinkenplugins.egg-info/pbr.json
shinkenplugins.egg-info/requires.txt
shinkenplugins.egg-info/top_level.txt
shinkenplugins/helpers/__init__.py
shinkenplugins/helpers/argparse/__init__.py
shinkenplugins/helpers/argparse/parsing/__init__.py
shinkenplugins/helpers/argparse/parsing/bytes.py
shinkenplugins/plugins/__init__.py
shinkenplugins/tools/__init__.py
shinkenplugins/tools/tests/__init__.py
shinkenplugins/tools/tests/netecho.py
shinkenplugins/tools/tests/tests.py