Metadata-Version: 1.0
Name: shinkenplugins
Version: 0.4.2
Summary: Shinken plugins wrapper library.
Home-page: https://github.com/savoirfairelinux/sfl-shinken-plugins
Author: Grégory Starck
Author-email: gregory.starck@savoirfairelinux.com
License: GPL3+
Platform: any
